syncing/__init__.py
syncing/_version.py
syncing/cli.py
syncing/model/__init__.py
syncing/model/interp.py
syncing/rw/__init__.py
syncing/rw/read.py
syncing/rw/write.py
syncing-1.0.9.dist-info/AUTHORS.rst
syncing-1.0.9.dist-info/LICENSE.txt
syncing-1.0.9.dist-info/METADATA
syncing-1.0.9.dist-info/WHEEL
syncing-1.0.9.dist-info/entry_points.txt
syncing-1.0.9.dist-info/top_level.txt
syncing-1.0.9.dist-info/RECORD
