Metadata-Version: 2.1
Name: syncing
Version: 1.0.9
Summary: Time series synchronisation and resample library.
Home-page: https://github.com/vinci1it2000/syncing
Download-URL: https://github.com/vinci1it2000/syncing/tarball/v1.0.9
Author: Vincenzo Arcidiacono
Author-email: vinci1it2000@gmail.com
License: EUPL 1.1+
Project-URL: Documentation, http://syncing.readthedocs.io
Project-URL: Issue tracker, https://github.com/vinci1it2000/syncing/issues
Project-URL: Donate, https://donorbox.org/syncing
Keywords: python,utility,library,synchronise,data,scientific,engineering,resample,time series
Classifier: Programming Language :: Python
Classifier: Programming Language :: Python :: 3.6
Classifier: Programming Language :: Python :: 3.7
Classifier: Programming Language :: Python :: 3.8
Classifier: Programming Language :: Python :: 3.9
Classifier: Programming Language :: Python :: 3.10
Classifier: Programming Language :: Python :: 3.11
Classifier: Programming Language :: Python :: Implementation :: CPython
Classifier: Development Status :: 5 - Production/Stable
Classifier: Natural Language :: English
Classifier: Intended Audience :: Developers
Classifier: Intended Audience :: Science/Research
Classifier: License :: OSI Approved :: European Union Public Licence 1.1 (EUPL 1.1)
Classifier: Operating System :: MacOS :: MacOS X
Classifier: Operating System :: Microsoft :: Windows
Classifier: Operating System :: POSIX
Classifier: Operating System :: Unix
Classifier: Operating System :: OS Independent
Classifier: Topic :: Scientific/Engineering
Classifier: Topic :: Scientific/Engineering :: Information Analysis
Classifier: Topic :: Software Development :: Libraries :: Python Modules
Classifier: Topic :: Utilities
License-File: LICENSE.txt
License-File: AUTHORS.rst
Requires-Dist: numpy
Requires-Dist: openpyxl
Requires-Dist: pandas
Requires-Dist: scipy
Requires-Dist: schedula >=1.1.1
Requires-Dist: xlrd >=1.0.0
Provides-Extra: all
Requires-Dist: Pygments ; extra == 'all'
Requires-Dist: click ; extra == 'all'
Requires-Dist: click-log ; extra == 'all'
Requires-Dist: docutils ; extra == 'all'
Requires-Dist: flask ; extra == 'all'
Requires-Dist: graphviz ; extra == 'all'
Requires-Dist: jinja2 ; extra == 'all'
Requires-Dist: regex ; extra == 'all'
Provides-Extra: cli
Requires-Dist: click ; extra == 'cli'
Requires-Dist: click-log ; extra == 'cli'
Provides-Extra: dev
Requires-Dist: Pygments ; extra == 'dev'
Requires-Dist: click ; extra == 'dev'
Requires-Dist: click-log ; extra == 'dev'
Requires-Dist: docutils ; extra == 'dev'
Requires-Dist: flask ; extra == 'dev'
Requires-Dist: graphviz ; extra == 'dev'
Requires-Dist: jinja2 ; extra == 'dev'
Requires-Dist: regex ; extra == 'dev'
Requires-Dist: wheel ; extra == 'dev'
Requires-Dist: sphinx ; extra == 'dev'
Requires-Dist: gitchangelog ; extra == 'dev'
Requires-Dist: mako ; extra == 'dev'
Requires-Dist: sphinx-rtd-theme ; extra == 'dev'
Requires-Dist: ddt ; extra == 'dev'
Requires-Dist: sphinxcontrib-restbuilder ; extra == 'dev'
Requires-Dist: coveralls ; extra == 'dev'
Requires-Dist: sphinx-click ; extra == 'dev'
Requires-Dist: matplotlib ; extra == 'dev'
Provides-Extra: plot
Requires-Dist: graphviz ; extra == 'plot'
Requires-Dist: regex ; extra == 'plot'
Requires-Dist: flask ; extra == 'plot'
Requires-Dist: Pygments ; extra == 'plot'
Requires-Dist: jinja2 ; extra == 'plot'
Requires-Dist: docutils ; extra == 'plot'
